hisv/__init__.py
hisv/bamToMatrix.py
hisv/combineIntraResult.py
hisv/combineResult.py
hisv/coolToMatrix.py
hisv/hicToMatrix.py
hisv/normCove.py
hisv/utils.py
hisv-2.0.1.data/scripts/HiSV
hisv-2.0.1.data/scripts/SV_type
hisv-2.0.1.data/scripts/determin_breakpoint
hisv-2.0.1.data/scripts/hicToMatrix.py
hisv-2.0.1.data/scripts/hiccovert
hisv-2.0.1.data/scripts/runHiSV_hic
hisv-2.0.1.dist-info/LICENSE
hisv-2.0.1.dist-info/METADATA
hisv-2.0.1.dist-info/WHEEL
hisv-2.0.1.dist-info/top_level.txt
hisv-2.0.1.dist-info/RECORD
