Metadata-Version: 2.1
Name: hisv
Version: 2.0.1
Summary: A computational pipeline for structural variation detection from Hi-C data
Home-page: https://github.com/GaoLabXDU/HiSV
Author: Li Junping
Author-email: lijunping02@qq.com
License: MIT Licence
Keywords: Hi-C,structural variation,control-free
Platform: any
License-File: LICENSE
Requires-Dist: numpy ==1.21.6
Requires-Dist: pandas ==1.3.5
Requires-Dist: pyBigWig ==0.3.22
Requires-Dist: prox-tv ==3.3.0
Requires-Dist: pysam ==0.21.0
Requires-Dist: pytest ==7.4.0
Requires-Dist: pygam ==0.8.0
Requires-Dist: scikit-learn ==1.0.2
Requires-Dist: cooler ==0.9.2
